docdocgo/__init__.py
docdocgo/core.py
docdocgo/styling.py
docdocgo/utils.py
docdocgo-0.1.0.dist-info/licenses/LICENSE
docdocgo-0.1.0.dist-info/METADATA
docdocgo-0.1.0.dist-info/WHEEL
docdocgo-0.1.0.dist-info/top_level.txt
docdocgo-0.1.0.dist-info/RECORD
