Metadata-Version: 2.4
Name: docdocgo
Version: 0.1.0
Summary: Insert pandas DataFrames as tables into Microsoft Word documents
Author-email: docdocgo <docdocgo@example.com>
License-Expression: MIT
Keywords: pandas,docx,word,tables,documents
Classifier: Development Status :: 4 - Beta
Classifier: Intended Audience :: Developers
Classifier: Intended Audience :: Science/Research
Classifier: Programming Language :: Python :: 3
Classifier: Programming Language :: Python :: 3.9
Classifier: Programming Language :: Python :: 3.10
Classifier: Programming Language :: Python :: 3.11
Classifier: Programming Language :: Python :: 3.12
Classifier: Topic :: Office/Business :: Office Suites
Classifier: Topic :: Scientific/Engineering
Requires-Python: >=3.9
License-File: LICENSE
Requires-Dist: python-docx>=1.1.0
Requires-Dist: pandas>=1.5.0
Provides-Extra: dev
Requires-Dist: pytest>=7.0.0; extra == "dev"
Requires-Dist: pytest-cov>=4.0.0; extra == "dev"
Dynamic: license-file
